absplit/__init__.py
absplit/data.py
absplit/ga.py
absplit/log.py
absplit/param.py
absplit/tutorials.py
absplit-1.4.6.data/data/calculation_diagram.png
absplit-1.4.6.data/data/logo.jpeg
absplit-1.4.6.dist-info/licenses/LICENSE
absplit-1.4.6.dist-info/WHEEL
absplit-1.4.6.dist-info/METADATA
absplit-1.4.6.dist-info/RECORD
